f1/__init__.py
f1/models.py
f1/schedule.py
tests/__init__.py
tests/integration/__init__.py
tests/integration/test_schedule.py
tests/unit/__init__.py
f1_api_wrapper-0.0.3.dist-info/LICENSE
f1_api_wrapper-0.0.3.dist-info/METADATA
f1_api_wrapper-0.0.3.dist-info/WHEEL
f1_api_wrapper-0.0.3.dist-info/top_level.txt
f1_api_wrapper-0.0.3.dist-info/RECORD
